basic_bar/__init__.py
basic_bar/basic_bar.py
tests/__init__.py
tests/test_basic_bar.py
basic_bar-0.5.dist-info/LICENSE
basic_bar-0.5.dist-info/METADATA
basic_bar-0.5.dist-info/WHEEL
basic_bar-0.5.dist-info/top_level.txt
basic_bar-0.5.dist-info/RECORD
